deepview/validator/__init__.py
deepview/validator/__main__.py
deepview/validator/exceptions.py
deepview/validator/datasets/__init__.py
deepview/validator/datasets/arrow.py
deepview/validator/datasets/base.py
deepview/validator/datasets/core.py
deepview/validator/datasets/darknet.py
deepview/validator/datasets/instance.py
deepview/validator/datasets/tfrecord.py
deepview/validator/datasets/utils.py
deepview/validator/evaluators/__init__.py
deepview/validator/evaluators/combinedevaluator.py
deepview/validator/evaluators/core.py
deepview/validator/evaluators/detectionevaluator.py
deepview/validator/evaluators/parameters.py
deepview/validator/evaluators/poseevaluator.py
deepview/validator/evaluators/segmentationevaluator.py
deepview/validator/evaluators/utils.py
deepview/validator/metrics/__init__.py
deepview/validator/metrics/core.py
deepview/validator/metrics/detectiondata.py
deepview/validator/metrics/detectionmatch.py
deepview/validator/metrics/detectionmetrics.py
deepview/validator/metrics/detectionutils.py
deepview/validator/metrics/posedata.py
deepview/validator/metrics/posemetrics.py
deepview/validator/metrics/poseutils.py
deepview/validator/metrics/segmentationdata.py
deepview/validator/metrics/segmentationmetrics.py
deepview/validator/metrics/segmentationutils.py
deepview/validator/metrics/summary.py
deepview/validator/runners/__init__.py
deepview/validator/runners/core.py
deepview/validator/runners/deepviewrt.py
deepview/validator/runners/hailo.py
deepview/validator/runners/keras.py
deepview/validator/runners/offline.py
deepview/validator/runners/onnx.py
deepview/validator/runners/tensorrt.py
deepview/validator/runners/tflite.py
deepview/validator/runners/modelclient/__init__.py
deepview/validator/runners/modelclient/core.py
deepview/validator/runners/modelclient/detection.py
deepview/validator/runners/modelclient/segmentation.py
deepview/validator/visualize/__init__.py
deepview/validator/visualize/detectiondraw.py
deepview/validator/visualize/posedraw.py
deepview_validator-3.3.0.dist-info/METADATA
deepview_validator-3.3.0.dist-info/WHEEL
deepview_validator-3.3.0.dist-info/entry_points.txt
deepview_validator-3.3.0.dist-info/top_level.txt
deepview_validator-3.3.0.dist-info/RECORD
