Metadata-Version: 2.1
Name: deepview-validator
Version: 3.3.0
Summary: DeepView Validator
Home-page: http://www.au-zone.com
Author: Au-Zone Technologies
Author-email: support@au-zone.com
License: PROPRIETARY
Platform: UNKNOWN
Requires-Dist: tqdm (>=4.64.0)
Requires-Dist: Pillow (>=9)
Requires-Dist: PyYAML (>=6.0)
Requires-Dist: matplotlib (>=3.5.0)
Requires-Dist: urllib3 (>=1.26.0)
Requires-Dist: requests (~=2.28.2)
Requires-Dist: numpy
Requires-Dist: deepview-datasets (~=0.3.0)
Provides-Extra: hailo
Requires-Dist: numpy (==1.23.3) ; extra == 'hailo'
Requires-Dist: hailort (~=4.15.0) ; extra == 'hailo'
Provides-Extra: keras
Requires-Dist: tensorflow (<2.16.0,>=2.8.0) ; extra == 'keras'
Requires-Dist: torchvision (~=0.15.2) ; extra == 'keras'
Provides-Extra: onnx
Requires-Dist: onnxruntime-gpu (~=1.16.3) ; extra == 'onnx'
Requires-Dist: tensorflow (<2.16.0,>=2.8.0) ; extra == 'onnx'
Requires-Dist: torchvision (~=0.15.2) ; extra == 'onnx'
Provides-Extra: test
Requires-Dist: pytest (~=7.4.0) ; extra == 'test'
Provides-Extra: tflite
Requires-Dist: tensorflow (<2.16.0,>=2.8.0) ; extra == 'tflite'
Requires-Dist: torchvision (~=0.15.2) ; extra == 'tflite'
